oneevent/__init__.py
oneevent/admin.py
oneevent/apps.py
oneevent/context_processors.py
oneevent/forms.py
oneevent/models.py
oneevent/tests.py
oneevent/tz_utils.py
oneevent/unicode_csv.py
oneevent/urls.py
oneevent/views.py
oneevent/migrations/0001_initial.py
oneevent/migrations/0002_event_employees_exception_groups.py
oneevent/migrations/0003_auto_category.py
oneevent/migrations/0004_fix_unique_category.py
oneevent/migrations/0005_create_employee_contractor_categories.py
oneevent/migrations/0006_remove_employee_contractor_fields.py
oneevent/migrations/0007_auto_20151212_1805.py
oneevent/migrations/0008_delete_message.py
oneevent/migrations/0009_event_timezone.py
oneevent/migrations/0010_remove_event_city.py
oneevent/migrations/0011_delete_user_cascade_to_events.py
oneevent/migrations/__init__.py
oneevent/static/OneEvent/OneEvent.css
oneevent/static/OneEvent/OneEvent.js
oneevent/templates/oneevent/base.html
oneevent/templates/oneevent/base_confirmation.html
oneevent/templates/oneevent/booking_cancel.html
oneevent/templates/oneevent/booking_create_on_behalf.html
oneevent/templates/oneevent/booking_payment_confirm.html
oneevent/templates/oneevent/booking_payment_exempt.html
oneevent/templates/oneevent/booking_update.html
oneevent/templates/oneevent/booking_update_with_sessions.html
oneevent/templates/oneevent/choice_delete.html
oneevent/templates/oneevent/choice_edit.html
oneevent/templates/oneevent/event_description_panel_part.html
oneevent/templates/oneevent/event_manage.html
oneevent/templates/oneevent/event_update.html
oneevent/templates/oneevent/events_list.html
oneevent/templates/oneevent/navbar_auth.html
oneevent/templates/oneevent/navbar_auth_avatar.html
oneevent/templates/oneevent/navbar_auth_extra_actions.html
oneevent/templates/oneevent/user_delete.html
oneevent/templates/registration/login.html
django_oneevent-1.2.0.dist-info/LICENSE
django_oneevent-1.2.0.dist-info/METADATA
django_oneevent-1.2.0.dist-info/WHEEL
django_oneevent-1.2.0.dist-info/top_level.txt
django_oneevent-1.2.0.dist-info/RECORD
