Metadata-Version: 2.1
Name: django-oneevent
Version: 1.2.0
Summary: A Django app to manage registration to events.
Home-page: https://github.com/gchazot/OneEvent
Author: Germain CHAZOT
Author-email: g.chazot@gmail.com
License: License :: OSI Approved :: MIT License
Classifier: Development Status :: 6 - Mature
Classifier: Environment :: Web Environment
Classifier: Framework :: Django
Classifier: Framework :: Django :: 2.1
Classifier: Framework :: Django :: 2.2
Classifier: Framework :: Django :: 3.0
Classifier: Framework :: Django :: 3.1
Classifier: Framework :: Django :: 3.2
Classifier: Intended Audience :: Developers
Classifier: Intended Audience :: Information Technology
Classifier: License :: OSI Approved :: MIT License
Classifier: Operating System :: OS Independent
Classifier: Programming Language :: Python
Classifier: Programming Language :: Python :: 3
Classifier: Programming Language :: Python :: 3 :: Only
Classifier: Programming Language :: Python :: 3.6
Classifier: Programming Language :: Python :: 3.7
Classifier: Programming Language :: Python :: 3.8
Classifier: Programming Language :: Python :: 3.9
Classifier: Programming Language :: Python :: 3.10
Classifier: Topic :: Internet :: WWW/HTTP
Classifier: Topic :: Internet :: WWW/HTTP :: Dynamic Content
Requires-Python: ~=3.6
License-File: LICENSE
Requires-Dist: django-crispy-forms (~=1.8)
Requires-Dist: icalendar (~=4.0)
Requires-Dist: django-timezone-field (>=3.1)
Provides-Extra: test
Requires-Dist: Django (<4) ; extra == 'test'
Requires-Dist: django-debug-toolbar ; extra == 'test'
Requires-Dist: django-extensions ; extra == 'test'
Requires-Dist: black ; extra == 'test'
Requires-Dist: flake8 ; extra == 'test'
